actual_admin_docs/__init__.py
actual_admin_docs/apps.py
actual_admin_docs/static/actual-admin-docs.css
actual_admin_docs/templates/admin/docs/page.html
actual_admin_docs/tests/__init__.py
actual_admin_docs/tests/sample_docs/img/cat_studying_glasses.jpg
actual_admin_docs/tests/sample_docs/index.md
actual_admin_docs/tests/sample_docs/markdown-sample.md
actual_admin_docs/tests/sample_docs/subfolder/another-file.md
actual_admin_docs/tests/sample_docs/subfolder/index.md
actual_admin_docs/tests/sample_docs/subfolder/subfolder with spaces/another file with spaces.md
actual_admin_docs/tests/test_docs.py
actual_admin_docs/tests/testproject/__init__.py
actual_admin_docs/tests/testproject/settings.py
actual_admin_docs/tests/testproject/urls.py
actual_admin_docs/urls.py
actual_admin_docs/views.py
django_actual_admin_docs-0.5.dist-info/METADATA
django_actual_admin_docs-0.5.dist-info/WHEEL
django_actual_admin_docs-0.5.dist-info/RECORD
