Metadata-Version: 2.1
Name: django-actual-admin-docs
Version: 0.5
Summary: Render Markdown documentation in the Django Admin.
Home-page: https://github.com/bartTC/django-actual-admin-docs
License: MIT
Author: Martin Mahner
Author-email: martin@mahner.org
Requires-Python: >=3.9,<4.0
Classifier: Development Status :: 5 - Production/Stable
Classifier: Environment :: Web Environment
Classifier: Framework :: Django
Classifier: Intended Audience :: Developers
Classifier: License :: OSI Approved :: MIT License
Classifier: Operating System :: OS Independent
Classifier: Programming Language :: Python
Classifier: Programming Language :: Python :: 3
Classifier: Programming Language :: Python :: 3.9
Classifier: Programming Language :: Python :: 3.10
Classifier: Programming Language :: Python :: 3.11
Classifier: Programming Language :: Python :: 3.12
Classifier: Programming Language :: Python :: 3.13
Requires-Dist: django
Requires-Dist: markdown-it-py[linkify,plugins] (>=3.0.0,<4.0.0)
